{
  "kind": "collectionType",
  "collectionName": "authors",
  "info": {
    "singularName": "author",
    "pluralName": "authors",
    "displayName": "Author",
    "description": ""
  },
  "options": {
    "draftAndPublish": true
  },
  "pluginOptions": {},
  "attributes": {
    "name": {
      "type": "string",
      "required": true,
      "maxLength": 16,
      "minLength": 1,
      "unique": true
    },
    "image": {
      "type": "media",
      "multiple": false,
      "required": true,
      "allowedTypes": [
        "images"
      ]
    },
    "blurb": {
      "type": "text"
    },
    "user": {
      "type": "relation",
      "relation": "oneToOne",
      "target": "admin::user",
      "private": true
    },
    "articles": {
      "type": "relation",
      "relation": "oneToMany",
      "target": "api::article.article",
      "mappedBy": "author"
    }
  }
}
